HISTORY.md
LICENSE.md
MANIFEST.in
README.md
setup.py
stringscore/__init__.py
stringscore/liquidmetal.py
stringscore/quicksilver.py
stringscore.egg-info/PKG-INFO
stringscore.egg-info/SOURCES.txt
stringscore.egg-info/dependency_links.txt
stringscore.egg-info/not-zip-safe
stringscore.egg-info/top_level.txt