Metadata-Version: 1.1
Name: stringscore
Version: 0.1.0
Summary: An algorithm provides scores between 0.0 (no match) to 1.0 (perfect match) for a comparison of two strings.
Home-page: https://github.com/bcse/stringscore
Author: Grey Lee
Author-email: bcse@bcse.tw
License: MIT
Keywords: stringscore
Platform: UNKNOWN
Classifier: Development Status :: 3 - Alpha
Classifier: Intended Audience :: Developers
Classifier: License :: OSI Approved :: MIT License
Classifier: Operating System :: OS Independent
Classifier: Programming Language :: Python
Classifier: Programming Language :: Python :: 2
Classifier: Programming Language :: Python :: 2.5
Classifier: Programming Language :: Python :: 2.6
Classifier: Programming Language :: Python :: 2.7
Classifier: Programming Language :: Python :: 3
Classifier: Programming Language :: Python :: 3.1
Classifier: Programming Language :: Python :: 3.2
Classifier: Programming Language :: Python :: 3.3
Classifier: Topic :: Software Development :: Libraries :: Python Modules
